kito/__init__.py
kito/engine.py
kito/module.py
kito/callbacks/__init__.py
kito/callbacks/callback_base.py
kito/callbacks/csv_logger.py
kito/callbacks/ddp_aware_callback.py
kito/callbacks/early_stopping_callback.py
kito/callbacks/modelcheckpoint.py
kito/callbacks/tensorboard_callback_images.py
kito/callbacks/tensorboard_callbacks.py
kito/callbacks/txt_logger.py
kito/config/__init__.py
kito/config/moduleconfig.py
kito/data/__init__.py
kito/data/datapipeline.py
kito/data/datasets.py
kito/data/preprocessed_dataset.py
kito/data/preprocessing.py
kito/data/registry.py
kito/losses/__init__.py
kito/losses/builtin.py
kito/losses/custom.py
kito/losses/registry.py
kito/losses/utils.py
kito/strategies/__init__.py
kito/strategies/logger_strategy.py
kito/strategies/progress_bar_strategy.py
kito/strategies/readiness_validator.py
kito/utils/__init__.py
kito/utils/decorators.py
kito/utils/gpu_utils.py
kito/utils/loss_utils.py
kito/utils/ssim_utils.py
pytorch_kito-0.2.1.dist-info/licenses/LICENSE
pytorch_kito-0.2.1.dist-info/METADATA
pytorch_kito-0.2.1.dist-info/WHEEL
pytorch_kito-0.2.1.dist-info/top_level.txt
pytorch_kito-0.2.1.dist-info/RECORD
