Metadata-Version: 2.4
Name: pytorch-kito
Version: 0.2.1
Summary: Effortless PyTorch training - define your model, Kito handles the rest
Author-email: Giuseppe Costantino <giuseppe.costantino95@gmail.com>
License: MIT License
Project-URL: Homepage, https://github.com/gcostantino/kito
Project-URL: Documentation, https://kito.readthedocs.io
Project-URL: Repository, https://github.com/gcostantino/kito
Project-URL: Bug Tracker, https://github.com/gcostantino/kito/issues
Keywords: pytorch,deep-learning,machine-learning,training,automation
Classifier: Development Status :: 3 - Alpha
Classifier: Intended Audience :: Science/Research
Classifier: Intended Audience :: Developers
Classifier: License :: OSI Approved :: MIT License
Classifier: Programming Language :: Python :: 3
Classifier: Programming Language :: Python :: 3.9
Classifier: Programming Language :: Python :: 3.10
Classifier: Programming Language :: Python :: 3.11
Classifier: Topic :: Scientific/Engineering
Classifier: Topic :: Scientific/Engineering :: Artificial Intelligence
Requires-Python: >=3.9
License-File: LICENSE
Requires-Dist: torch>=2.0.0
Requires-Dist: numpy>=1.20.0
Requires-Dist: h5py>=3.0.0
Requires-Dist: torchsummary>=1.5.1
Requires-Dist: packaging>=20.0
Requires-Dist: tensorboard>=2.10.0
Requires-Dist: pkbar>=0.5
Provides-Extra: dev
Requires-Dist: pytest>=7.0; extra == "dev"
Requires-Dist: pytest-cov>=4.0; extra == "dev"
Requires-Dist: pytest-mock>=3.10; extra == "dev"
Requires-Dist: black>=23.0; extra == "dev"
Requires-Dist: ruff>=0.1.0; extra == "dev"
Provides-Extra: tensorboard
Requires-Dist: tensorboard>=2.10.0; extra == "tensorboard"
Provides-Extra: docs
Requires-Dist: sphinx>=5.0; extra == "docs"
Requires-Dist: sphinx-rtd-theme>=1.0; extra == "docs"
Provides-Extra: all
Requires-Dist: tensorboard>=2.10.0; extra == "all"
Requires-Dist: pytest>=7.0; extra == "all"
Requires-Dist: pytest-cov>=4.0; extra == "all"
Requires-Dist: pytest-mock>=3.10; extra == "all"
Requires-Dist: black>=23.0; extra == "all"
Requires-Dist: ruff>=0.1.0; extra == "all"
Requires-Dist: sphinx>=5.0; extra == "all"
Requires-Dist: sphinx-rtd-theme>=1.0; extra == "all"
Dynamic: license-file
